{
	"absolute_value": 0,
	"align_labels_right": 0,
	"creation": "2024-06-04 04:59:24.275841",
	"css": " .container_ {\n            width:100%;\n            display: flex;\n            padding-right: 0px;\n            padding-left: 0px;\n            margin-right: auto;\n            margin-left: auto;\n        }\n.box {\n    flex: 1; /* This makes each div take up equal space */\n    margin: 10px;\n}\n.print-format td{\n    padding:2px !important;\n}\n.print-format th{\n    padding:2px !important;\n}\ntable{\n    font-size:12px!important;\n}",
	"custom_format": 1,
	"default_print_language": "en",
	"disabled": 0,
	"doc_type": "Check Run",
	"docstatus": 0,
	"doctype": "Print Format",
	"font_size": 14,
	"html": "<div id=\"header-html\" class=\"hidden-pdf\">\n\t<div class=\"print-heading\">\n\t\t<h2>\n\t\t\t<div>Check Run</div>\n\t\t\t<small class=\"sub-heading\">ACC-CR-2024-00001</small>\n\t\t</h2>\n\t</div>\n</div>\n<div class=\"container_\">\n    <div class=\"box\">\n        <p>Check Run End Date:</p>\n        <b>{{doc.end_date or  ''}}</b>\n    </div>\n    <div class=\"box\">\n        <p>Initial Check Number:</p>\n        <b>{{ doc.initial_check_number}}</b>\n    </div>\n    <div class=\"box\">\n        <p>Company</p>\n        <b>{{ doc.company }}</b>\n    </div>\n</div>\n<div class=\"container_\">\n    <div class=\"box\">\n        <p>Posting Date:</p>\n        <b>{{doc.posting_date or  ''}}</b>\n    </div>\n    <div class=\"box\">\n        <p>Final Check Number:</p>\n        <b>{{ doc.final_check_number }}</b>\n    </div>\n    <div class=\"box\">\n        <p>Paid From (Bank Account):</p>\n        <b>{{ doc.bank_account }}</b>\n    </div>\n</div>\n<div class=\"container_\">\n    <div class=\"box\">\n        <p>Beginning Bank Account Balance:</p>\n        <b>{{frappe.format(doc.beg_balance,{'fieldtype':\"Currency\"} ) or  ''}}</b>\n    </div>\n    <div class=\"box\">\n        <p>Amount in Check Run</p>\n        <b>{{frappe.format(doc.amount_check_run ,{'fieldtype':\"Currency\"} ) or  ''}}</b>\n    </div>\n    <div class=\"box\">\n        <p>Accounts Payable:</p>\n        <b>{{ doc.pay_to_account }}</b>\n    </div>\n</div>\n{% set pe_list = frappe.db.get_list(\"Payment Entry\", {\"check_run\":doc.name}) %}\n<table width=\"100%\" border=1>\n    <tbody>\n        <tr>\n            <th>Party</th>\n            <th>Document</th>\n            <th>Document Date</th>\n            <th>Outstanding Amount</th>\n            <th>Due Date</th>\n            <th>Reference</th>\n        </tr>\n    \n    {% for row in pe_list %}\n    {% set doc_ = frappe.get_doc(\"Payment Entry\", row.name) %}\n    {% for d in doc_.references %}\n        <tr>\n            <td>{{ doc_.party }}</td>\n            <td>{{ d.reference_name }}</td>\n            <td>{{ frappe.db.get_value(d.reference_doctype, d.reference_name, \"posting_date\") or ''}}</td>\n            <td>{{ doc_.paid_amount or '' }}</td>\n            <td>{{ frappe.db.get_value(d.reference_doctype, d.reference_name, \"due_date\") or '' }}</td>\n            <td>{{ doc_.name }}</td>\n        </tr>\n    {% endfor %}\n    {% endfor %}\n    </tbody>\n</table>\n\n    \n    \n\n",
	"idx": 0,
	"line_breaks": 0,
	"margin_bottom": 15.0,
	"margin_left": 15.0,
	"margin_right": 15.0,
	"margin_top": 15.0,
	"modified": "2024-06-06 03:54:20.194111",
	"modified_by": "Administrator",
	"module": "Check Run",
	"name": "Check Run",
	"owner": "Administrator",
	"page_number": "Hide",
	"print_format_builder": 0,
	"print_format_builder_beta": 0,
	"print_format_type": "Jinja",
	"raw_printing": 0,
	"show_section_headings": 0,
	"standard": "Yes"
}
